[
  {
    "title": "The Shawshank Redemption",
    "cast": ["Tim Robbins", "Morgan Freeman"],
    "category": "Drama",
    "releaseDate": "1994-10-14",
    "budget": 25000000
  },
  {
    "title": "The Godfather",
    "cast": ["Marlon Brando", "Al Pacino"],
    "category": "Crime",
    "releaseDate": "1972-03-24",
    "budget": 6000000
  },
  {
    "title": "The Dark Knight",
    "cast": ["Christian Bale", "Heath Ledger"],
    "category": "Action",
    "releaseDate": "2008-07-18",
    "budget": 185000000
  },
  {
    "title": "Schindler's List",
    "cast": ["Liam Neeson", "Ben Kingsley"],
    "category": "Biography",
    "releaseDate": "1993-12-15",
    "budget": 22000000
  },
  {
    "title": "Pulp Fiction",
    "cast": ["John Travolta", "Uma Thurman"],
    "category": "Crime",
    "releaseDate": "1994-10-14",
    "budget": 8000000
  },
  {
    "title": "The Lord of the Rings: The Return of the King",
    "cast": ["Elijah Wood", "Viggo Mortensen"],
    "category": "Adventure",
    "releaseDate": "2003-12-17",
    "budget": 94000000
  },
  {
    "title": "Forrest Gump",
    "cast": ["Tom Hanks", "Robin Wright"],
    "category": "Drama",
    "releaseDate": "1994-07-06",
    "budget": 55000000
  },
  {
    "title": "The Matrix",
    "cast": ["Keanu Reeves", "Laurence Fishburne"],
    "category": "Action",
    "releaseDate": "1999-03-31",
    "budget": 63000000
  },
  {
    "title": "Inception",
    "cast": ["Leonardo DiCaprio", "Joseph Gordon-Levitt"],
    "category": "Action",
    "releaseDate": "2010-07-16",
    "budget": 160000000
  },
  {
    "title": "The Silence of the Lambs",
    "cast": ["Jodie Foster", "Anthony Hopkins"],
    "category": "Crime",
    "releaseDate": "1991-02-14",
    "budget": 19000000
  },
  {
    "title": "The Green Mile",
    "cast": ["Tom Hanks", "Michael Clarke Duncan"],
    "category": "Drama",
    "releaseDate": "1999-12-10",
    "budget": 60000000
  },
  {
    "title": "Saving Private Ryan",
    "cast": ["Tom Hanks", "Matt Damon"],
    "category": "Drama",
    "releaseDate": "1998-07-24",
    "budget": 70000000
  },
  {
    "title": "Gladiator",
    "cast": ["Russell Crowe", "Joaquin Phoenix"],
    "category": "Action",
    "releaseDate": "2000-05-05",
    "budget": 103000000
  },
  {
    "title": "Titanic",
    "cast": ["Leonardo DiCaprio", "Kate Winslet"],
    "category": "Romance",
    "releaseDate": "1997-12-19",
    "budget": 200000000
  },
  {
    "title": "Avatar",
    "cast": ["Sam Worthington", "Zoe Saldana"],
    "category": "Action",
    "releaseDate": "2009-12-18",
    "budget": 237000000
  }
]
